serenipy/__init__.py
serenipy/census-label-free.py
serenipy/census.py
serenipy/censuslf.py
serenipy/dtaselect.py
serenipy/dtaselectfilter.py
serenipy/ms2.py
serenipy/sqt.py
serenipy/utils.py
serenipy/idx/__init__.py
serenipy/idx/data.py
serenipy/idx/parser.py
serenipy/idx/serializer.py
serenipy/idx/utils.py
serenipy/project/__init__.py
serenipy/project/experiment.py
serenipy/project/file_types.py
serenipy/project/project.py
serenipy/project/search.py
serenipy-0.3.0.dist-info/licenses/LICENSE
serenipy-0.3.0.dist-info/METADATA
serenipy-0.3.0.dist-info/WHEEL
serenipy-0.3.0.dist-info/top_level.txt
serenipy-0.3.0.dist-info/RECORD
