Metadata-Version: 2.4
Name: serenipy
Version: 0.3.0
Summary: Python tools for data analysis and processing
Author-email: Patrick Garrett <pgarrett@scripps.edu>
License: MIT
Classifier: Programming Language :: Python :: 3
Classifier: License :: OSI Approved :: MIT License
Classifier: Operating System :: OS Independent
Requires-Python: >=3.8
License-File: LICENSE
Requires-Dist: pandas>=2.0.0
Dynamic: license-file
